spark/__init__.py
spark/core.py
spark/util/Errors.py
spark/util/HTMLColors.py
spark/util/IpyExit.py
spark/util/TypeSignature.py
spark/util/__init__.py
spark/util/core_methods.py
spark/util/decorators.py
spark/util/helper_functions/__init__.py
spark/util/helper_functions/arc_functions.py
spark/util/helper_functions/canvas_functions.py
spark/util/helper_functions/circle_functions.py
spark/util/helper_functions/ellipse_functions.py
spark/util/helper_functions/image_functions.py
spark/util/helper_functions/keyboard_functions.py
spark/util/helper_functions/line_functions.py
spark/util/helper_functions/misc_functions.py
spark/util/helper_functions/rect_functions.py
spark/util/helper_functions/square_functions.py
spark/util/helper_functions/text_functions.py
spark/util/helper_functions/triangle_functions.py
schulich_ignite-0.1.3.dist-info/LICENSE
schulich_ignite-0.1.3.dist-info/METADATA
schulich_ignite-0.1.3.dist-info/WHEEL
schulich_ignite-0.1.3.dist-info/top_level.txt
schulich_ignite-0.1.3.dist-info/RECORD
