Metadata-Version: 2.1
Name: schulich-ignite
Version: 0.1.3
Summary: Spark library for Shulich Ignite sessions
Home-page: https://github.com/Schulich-Ignite/spark
Author: Schulich Ignite
Author-email: info@shulichignite.com
License: UNKNOWN
Platform: UNKNOWN
Classifier: Programming Language :: Python :: 3
Classifier: License :: OSI Approved :: MIT License
Classifier: Framework :: IPython
Classifier: Operating System :: OS Independent
Requires-Python: >=3.8
Requires-Dist: ipywidgets
Requires-Dist: ipycanvas
Requires-Dist: ipyevents
